# 线程知识

> 尽量涉及这些知识：单线程扩展到并发编程，从并发编程深入到线程同步、线程安全、进程间通信



## 线程是什么

1. 线程是CPU调度和分派的最小单位，它可与同属于同一个进程的其他线程，共享进程所拥有的全部资源。
2. 一个进程下可以有多个线程，但至少有一个线程。

线程和进程的区别是什么？

1. 进程：进程是程序的一次执行过程，是一个动态概念。

2. 线程： 线程是进程的一部分，一个线程只能属于一个进程，而一个进程可以有多个线程，但至少有一个线程。

3. **根本区别：从资源使用的角度出发（资源就是计算机里的中央处理器，内存，文件，网络）。进程是操作系统资源分配的基本单位，而线程是任务调度和执行的基本单位。**

   - **在开销方面：**每个进程都有独立的代码和上下文（数据空间），进程的创建、销毁、切换产生大量的时间和空间的开销；而线程的切换开销小，因为线程有自己的程序计数器可以快速回复到上次执行的位置；并且线程可以看做是轻量级的进程，同一类线程共享资源。

   - **在系统资源方面：** 系统在运行时会为每个进程分配不同的内存空间，比如堆、栈；线程基本不拥有系统资源，只有一些运行时必不可少的资源，比如程序计数器、寄存器和栈，



## 线程的创建

> 创建线程的方式
>
> 1. 继承Thread类
>
> 2. 实现Runnable接口
>
> 3. 实现Callable

1.  ##### 继成`java.lang.Thread`, 重写run()方法

   ```java
   public class ThreadByExtendsThread extends Thread{
       @Override
       public void run() {
           super.run();
           for (int i = 0; i < 20; i++) {
               System.out.println("我在学习创建多线程====" + i);
           }
           System.out.println("==========");
       }
       public static void main(String[] args) {
           ThreadByExtendsThread thread1 = new ThreadByExtendsThread();
           ThreadByExtendsThread thread2 = new ThreadByExtendsThread();
           ThreadByExtendsThread thread3 = new ThreadByExtendsThread();
           thread1.start();
           thread2.start();
           System.out.println(Thread.currentThread().getName());
           //数字紊乱，发现不是按照i的顺序来执行的，有线程安全问题
       }
   }
   ```

2. ##### 实现Runnable接口，重写run()方法

   ```java
   public class ThreadByImplementRunnable implements Runnable{
   
       @Override
       public void run() {
           for (int i = 0; i < 20; i++) {
               System.out.println("我在听课====" + i);
           }
           System.out.println("==========");
       }
       public static void main(String[] args) {
           ThreadByImplementRunnable thread1 = new ThreadByImplementRunnable();
           new Thread(thread1).start();
           //或者也可以写成：
           //Thread t1 = new Thread(thread1);
           //t1.start();
       }
   }
   ```

> 继承Thread类和实现Callable接口这两种方式很相像，两种方式都需要重写run()方法，然后再调用Thread类的start()方法来启动线程。
>
> 本质没有明显的区别，但是写法有一些区别。第一种方式是继承Thread类，因为Java是单继承的，如果一个类继承了Thread类，那么这个类就不能再继承其他类了，在继承上有一些限制；第二种方式是为了解决第一种方式的单继承不灵活的问题；因此平常多使用的是第二种方式

3. ##### 实现Callable接口

```
/**
 * 1.实现Callable接口，需要返回值类型
 * 2.重写call方法，需要抛出异常
 * 3.创建目标对象
 * 4.创建线程执行服务： ExecutorService service = Executors.newFixedThreadPool(1);
 * 5.提交执行：Futrue<Boolean> result = service.submit();
 * 6.获取结果：Boolean r1 = result.get();
 * 7.关闭服务：service.shutdown();
 */
 
 public class ThreadByImplementsCallable implements Callable<Boolean> {

    private String url;
    private String name;

    public ThreadByImplementsCallable(String url,String name){
        this.url = url;
        this.name = name;
    }

    @Override
    public Boolean call() throws Exception {
        WebDownLoader webDownLoader = new WebDownLoader();
        webDownLoader.downLoader(url, name);
        System.out.println("下载了文件名为：" + name);
        return true;
    }

    public static void main(String[] args) {
        ThreadByImplementsCallable t1 = new ThreadByImplementsCallable("https://dss2.bdstatic.com/70cFvnSh_Q1YnxGkpoWK1HF6hhy/it/u=2763858159,801771131&fm=26&gp=0.jpg","图片1");
        ThreadByImplementsCallable t2 = new ThreadByImplementsCallable("https://dss2.bdstatic.com/70cFvnSh_Q1YnxGkpoWK1HF6hhy/it/u=2763858159,801771131&fm=26&gp=0.jpg","图片2");
        ThreadByImplementsCallable t3 = new ThreadByImplementsCallable("https://dss2.bdstatic.com/70cFvnSh_Q1YnxGkpoWK1HF6hhy/it/u=2763858159,801771131&fm=26&gp=0.jpg","图片3");

        //1.创建执行服务
        ExecutorService service = Executors.newFixedThreadPool(3);
        //2.提交执行
        Future<Boolean> r1 = service.submit(t1);
        Future<Boolean> r2 = service.submit(t2);
        Future<Boolean> r3 = service.submit(t3);
        //3.获取结果
        try {
            boolean rs1 = r1.get();
            boolean rs2 = r2.get();
            boolean rs3 = r3.get();
            //4.关闭服务
            service.shutdown();
        } catch (InterruptedException e) {
            e.printStackTrace();
        } catch (ExecutionException e) {
            e.printStackTrace();
        }

    }
}
```



## 线程的状态

1. 创建状态（New）：new Thread(); 创建完成以后需要为线程分配内存
2. 就绪状态（Runnable）：调用了start()方法，等待CPU的调度
3. 运行状态（Running）：执行run()方法
4. 阻塞状态（Blocking）：暂时停止执行线程，将线程挂起（sleep(), wait(), join(), 没有获取到锁都会使线程阻塞），可能将资源给其他线程使用
5. 死亡状态（Terminated）： 线程销毁(正常执行完毕、发生异常或者被打断interrupt()都会导致线程终止)



## 线程不安全的原因

线程不安全的原因是因为<u>主内存和工作内存数据不一致性和重排序</u>导致的；那这就需要我们去解决。

先了解一下Java的内存模型：

#### 1.1共享变量：

- 方法区和堆是所有线程共享的，所有线程均可以访问。如：静态变量是放在方法区的，数组、对象实例是放在堆内存中的。
- 虚拟机栈和本地方法栈、程序计数器是线程私有的。如：局部变量，方法定义参数和异常处理器参数不会在线程中共享。
- 共享区域的数据会出现线程安全问题，而非共享数据不会出现线程安全问题。

#### 1.2JMM内存模型

- 让我们来了解一下CPU 和主内存的读写速度。一级、二级、三级、主内存的访问时间，CPU的速度基本和第一级Cache一致。可见CPU的速度是主内存的100倍左右

  > 1st level cache / 1st level TLB   1ns
  >
  > 2nd level cache / 2nd level TLB   4ns
  >
  > 3rd level cache                   TLB   12ns
  >
  > Memory(DRAM)                         100ns

cpu处理数据可以简单认为是读取，运算，回写，在我们看来cpu处理速度高于内存。但是数据并不是直接就能使用通常要经过大量计算，如果在计算时大量访问内存会使得程序的性能会大幅下降（原因是访问内存的速度慢），内存访问次数越多，性能越差，所以才引入缓存从而减少cpu访问内存的次数。我们常常会在CPU(处理器)中加入**高速缓存（Cache Memory）**，也就是将数据缓存到处理器中，当处理器处理完数据后，再将处理的数据结果存储在内存中。

**Java线程之间的通信有Java内存模型（JMM）控制，JMM决定一个线程对共享变量的写入何时对其他线程可见。**

*共享变量是放在主内存中，每个线程都有属于自己的工作内存，并且会把位于主内存的共享变量拷贝到自己的工作内存中，之后的读写操作均使用位于工作内存的变量副本，并在某个时刻将工作内存的变量副本写回到主内存中。*



如图为JMM抽象示意图，线程A和线程B之间要完成通信的话，要经历如下两步：

1. 线程A从主内存中将共享变量读入线程A的工作内存后并进行操作，之后将数据重新写回到主内存中；
2. 线程B从主存中读取最新的共享变量

> 从这里就可以看出这里有时差性的问题，因此这里容易出现线程安全问题。
>
> <u>如果线程A更新了工作内存中的共享变量的副本，但是却没有及时回写到主内存，而此时线程B来读取数据，因此B读到的是过期的数据，这就出现了“脏读”现象。可以通过同步机制（控制不同线程间操作发生的相对顺序）来解决或者通过volatile关键字使得每次volatile变量都能够强制刷新到主内存，从而对每个线程都是可见的。</u>

#### 1.3重排序

重排序是指：在不改变程序执行结果的前提下，尽可能提高并行度。JMM对底层尽量减少约束，使其能发挥自身优势。在执行程序时，为了提高性能，编译器和处理器常常会对指令进行重排序。

**源代码 --》 1：编译器优化重排序 --》 2：指令级并行重排序 --》3：内存系统重排序 --》最终执行的指令序列**

1. 编译器优化的重排序。编译器在不改变单线程程序语义的前提下，可以重新安排语句的执行顺序；
2. 指令级并行的重排序。现在处理器采用了指令级并行技术来讲多条指令重叠执行。如果不存在数据依赖性，处理器可以改变语句对应机器指令的执行顺序；
3. 内存系统的重排序。由于处理器使用缓存和读/写缓冲区，这使得加载和存储操作看上去可能是在乱序执行的。 -- 没有理解

**

1属于编译器重排序，2和3统称为处理器重排序。这些3重排序会导致线程安全问题。

**针对编译器重排序，`JMM`的编译器重排序规则会禁止一些特定类型的编译器重排序；**

**针对处理器重排序，编译器在生成指令序列的时候会通过插入内存屏障指令来禁止某些特殊的处理器重排序。**



这个还没怎么了解

#### 1.4总结

- 在物理计算机中CPU为了提高处理速度，添加了高速缓存与CPU乱序执行

- Java定义了自身的**内存模型**是为了屏蔽掉不同硬件和操作系统的内存模型差异

- Java为了处理内存的不可见性与重排序的问题，定义了**Happens-Before 原则**

- Happens-Before 原则的理解：对于两个操作A和B，这两个操作可以在不同的线程中执行。如果A Happens-Before B，那么可以保证，当A操作执行完后，A操作的执行结果对B操作是可见的。



## 线程间的通信

线程间通信的模型有两种：共享内存和消息传递，以下方式都是基本这两种模型来实现的。线程通信常用的方式有

- `wait/notify` 等待
- `volatile` 内存共享
- `CountDownLatch` 并发工具

- `CyclicBarrier` 并发工具

#### 1.1`volatile`关键字

volatile关键字保证了数据的可见性。如何保证的呢？

volatile关键字修饰变量，即告知线程对该变量的访问必须从主内存中获取；对volatile变量的改变必须同步刷新到主内存中。

#### 1.2 等待通知机制 

`syncronized` 配套 `wait()/notify()`, `wait()/notifyAll()`



#### 1.3 wait() 和 sleep()区别

##### 1.来自不同的类

sleep()来自Thread类，wait()是Object类的方法。

sleep()是Thread的静态类方法，哪个线程调用，对应线程就去睡觉。

##### 2.有没有释放资源（释放锁）

最主要的是：**sleep()没有释放锁、wait()释放了锁，使得其他线程可以使用同步块或者方法。**

1. `sleep()`不让出系统资源；wait()是线程进入线程等待池等待，让出系统资源，其他线程可以占用CPU

2. `sleep(milliSeconds)`可以用时间指定使他自动唤醒过来，如果时间不到只能调用`interrupt()`强行打断； `wait()`一般不会加时间限制，因为如果wait()线程的运行资源不够，再出来也没有用需要等待其他线程调用`notify()/notifyAll()`唤醒等待池中的所有线程

   > sleep()是线程站着CPU去睡觉，其他线程不能占用CPU，OS认为该线程正在工作，因此sleep()是不让出系统资源的。
   >
   > wait()是让出系统资源，进入等待池等待，其他CPU可以占用CPU，wait()要等待其他线程调用`notify()/notifyAll()`方法唤醒等待池中的所有线程

##### 3.使用范围不同

1.wait(), notify(), notifyAll()只能在同步控制方法或者同步控制块里面使用，sleep可以在任何地方使用

##### 4.是否需要补货异常

sleep必须捕获异常，而wait，notify和notifyAll不需要捕获异常



# CAS锁

> 参考：https://juejin.cn/post/6844903564691652615

### CAS是什么

1.``CAS(Compare and swap) 或者 (Compare and exchange)`比较并替换或更新，比较和替换是线程并发时用到的一种技术

2.`**CAS`是原子操作，保证并发安全，而不是保证并发同步** 没有保证同步吗？ 不是底层用了lock吗？

3.`CAS`是CPU的一个指令。  疑问？CPU的吗？

4.`CAS`是非阻塞的、轻量级的乐观锁

### 为什么说CAS是乐观锁

乐观锁，严格来说乐观锁不是锁，通过原子性来保证数据的同步，比如说数据库的乐观锁，通过版本控制来实现等，所以CAS不会保证线程同步。**乐观的认为在数据更新期间没有其他线程影响。**

### CAS原理

`CAS(Compare and Swap)`比较并替换，就是将内存值(旧值From)更新为需要的值(新值To)，但是必须是 旧值From 等于 内存中的实际值时才会去更新。

有三个值：**V 内存地址存放的实际值；O 预期的值（旧值）；N 更新的新值**。当V和O相同时，也就是说旧值和内存中实际的值相同，表明该值没有被其他线程更改过，那么就更新值为N：更新的新值。反之，V和O不相同，表明该值已经被其他线程改过了则该旧值O不是最新版本的值了，所以不能将新值N赋给V，返回V即可。

当多个线程使用CAS操作一个变量是，只有一个线程会成功，并成功更新，其余会失败。失败的线程会重新尝试，当然也可以选择挂起线程

CAS应用

由于CAS 是CPU指令，我们只能通过`JNI`与操作系统交互，关于`CAS`的方法都在`sun.misc`包下的Unsafe的类里。`java.util.concurrent.automic`包下的原子类等通过CAS来实现原子操作。



#### CAS优缺点

- 优点
   非阻塞的轻量级的乐观锁，通过CPU指令实现，在资源竞争不激烈的情况下性能高，相比synchronized重量锁，synchronized会进行比较复杂的加锁，解锁和唤醒操作。
- 缺点
   （1）ABA问题 线程C、D,线程D将A修改为B后又修改为A,此时C线程以为A没有改变过，java的原子类AtomicStampedReference，通过控制变量值的版本来保证CAS的正确性。
   （2）自旋时间过长，消耗CPU资源， 如果资源竞争激烈，多线程自旋长时间消耗资源。








# Syncronized实现原理

## 1.使用场景

可以用在变量、代码块、方法中，根据Syncronized使用的位置有不同的

### 1.1syncronized用在方法上

**实例方法**

syncronized 用在实例方法上

被锁住的对象是：类的实例对象

```
//实例方法，锁住的是该类的实例对象
public syncronized void method(){
	...
}
```

**静态方法**

`syncronized` 用在静态方法上

被锁住的对象是类对象

```
//静态方法，锁住的是类对象
public static syncronized void method(){
	...
}
//或者
public void lockClass(){
	syncronized(ClassLock.class){
		...
	}
}

```

> **类锁和对象锁的区别：**
>
> 对象锁的疑问：如果有多个实例对象，那就会有多把锁吗 每个对象一把锁
>
> - 类锁：
>   - 类锁是一个class其中的静态方法或者静态变量在内存中只会加载初始化一份，所以，一旦一个静态方法被申明为syncronized，此类的所有的实例化对象在调用该方法时，共用同一把锁，称之为类锁。
>   - 类锁是加在类上的，而类信息是存在JVM方法区的，并且整个JVM只有一份，方法区是所有线程共享的，所以类锁是线程共享的。
>   - 线程获得对象锁的同时，也可以获得类锁，类锁和对象锁是两个不一样的锁，互不干扰
>
> - 对象锁
>   - 对象锁是当一个对象中有同步方法或者同步块，线程调用此对象进入该同步区域时，必须获得对象锁。如果此对象的对象锁被其他线程占用，则该线程进入阻塞队列，等待此锁释放（同步块正常返回或者抛异常终止，由JVM自动释放对象锁）
>   - 注意，方法锁也是一种对象锁。
>
> - ##### 重要：对象锁是用来控制实例方法之间的同步，而类锁是用来控制静态方法（或者静态变量互斥体）之间的同步的。

### 1.2syncronized用在代码块上

**实例对象、任意实例对象**

被锁住的对象是实例对象

```
//实例对象
syncronized(this){...}

//任意实例对象
String lock = "";
syncronized(lock){...}
```

**Class对象**

被锁住的对象是 Class对象

```
//被锁住的对象是 Class对象
syncronized(SyncronizedDemo.class){
	...
}
```

### 总结一下

| 分类   | 具体分类           | 被锁住的对象   | 是否线程共享锁 | 伪代码                                                       |                                                              |
| ------ | :----------------- | -------------- | -------------- | ------------------------------------------------------------ | ------------------------------------------------------------ |
| 变量   | 普通变量           | l类的实例对象  | 否             | private Object lock = new Object();<br/>synchronized (lock){...//do something} | 与静态变量做区分                                             |
|        | 静态变量           | 类对象         | 是             | private static Object lock = new Object();<br/>synchronized (lock){...//do something} |                                                              |
| 方法   | 实例方法           | 类的实例对象   | 否             | //实例方法，锁住的是该类的实例对象<br/>public syncronized void method(){...//do something} | 方法一旦执行，就独占该锁，一直到该方法返回时才将锁释放，此后阻塞的线程才能获得该锁，从而重新进入可执行状态 |
|        | 静态方法           | 类对象         | 是，线程共享锁 | //静态方法，锁住的是类对象<br/>public static syncronized void method(){...//do something} | 类锁是所有线程共享的锁，所以同一时刻，只能有一个线程使用加锁的的方法或方法体，不管是不是同一个实例。<br>Class用于描述类的基本信息：包括字段、构造方法、普通方法，在内存中只有一份Class类对象。Class类的对象是单例的(testClass.getClass() 同一个类的Class对象都是相同的) |
| 代码块 | 实例对象this       | 类的实例对象   | 否             | syncronized(this){...//do something}                         | this 指的是当前对象实例本身，所以，所有使用 `synchronized(this)`方式的方法都共享同一把锁。<br/>在使用同步`synchronized(this)`代码块时要注意，当一个线程访问object的一个`synchronized(this)`同步代码块时，其他线程对同一个object中所有其他`synchronized(this)`同步代码块的访问将被阻塞。这说明`synchronized`使用的对象监视器是同一个，即使用的锁是同一个。 |
|        | Class对象          | 类对象         | 是             | syncronized(SyncronizedDemo.class){...}                      |                                                              |
|        | 任意实例对象Object | Object实例对象 | 否             | String lock = "";<br/>syncronized(lock){...}                 |                                                              |



## 2.syncronized在字节码指令中的原理

`syncronized`在JVM的实现原理是基于进入和退出管理（Monitor）对象来实现同步。但`syncronized`关键字实现同步代码块和同步方法的不一样，代码块同步是使用 `monitorenter` 和 `monitorexit` 指令实现的，方法同步通过调用指令读取运行时常量池方法的`ACC_SYNCRONIZED` 标志来隐式实现的。

普通方法：`ACC_SYNCRONIZED` 

代码块： 对象锁（monitor）

在`cmd`中使用javap命令将class文件转成字节码指令，参数-v用于输出附加信息，-c用于对代码的反编译。

### 代码块、普通方法：

源代码如下：既有普通的同步方法，又有syncronized代码块。

```

/**
 * 查看对象锁和类锁:线程获得对象锁的同时，也可以获得类锁，类锁和对象锁是两个不一样的锁，互不干扰
 */
public class TestSynchronized {
    //对象锁
    public synchronized void test1() {
        int i = 5;
        while (i-- > 0) {
            System.out.println(Thread.currentThread().getName() + " : " + i);
            try {
                Thread.sleep(500);
            } catch (InterruptedException ie) {
            }
        }
    }
    //类锁
    public static synchronized void test2() {
        int i = 5;
        while (i-- > 0) {
            System.out.println(Thread.currentThread().getName() + " : " + i);
            try {
                Thread.sleep(500);
            } catch (InterruptedException ie) {
            }
        }
    }

    /**
     * 线程获得对象锁的同时，也可以获得类锁，类锁和对象锁是两个不一样的锁，互不干扰
     * @param args
     */
    public static void main(String[] args) {
        final TestSynchronized myt2 = new TestSynchronized();
        Thread test1 = new Thread(new Runnable() {
            public void run() {
                myt2.test1();
            }
        }, "test1");
        Thread test2 = new Thread(new Runnable() {
            public void run() {
                TestSynchronized.test2();
            }
        }, "test2");
        test1.start();
        test2.start();
//         TestRunnable tr=new TestRunnable();
//         Thread test3=new Thread(tr);
//         test3.start();
    }
}
```

### 指令

反编译的指令中，普通方法使用了flag标志ACC_SYNCRONIZED，说明方法是同步的。而代码块使用的是对象锁（monitor）- `monitorenter, monitorexit`

```
//警告，指令内容很长
$ javap -c -v TestSynchronized.class
Classfile /D:/ProjectCode/JavaLectrue/target/classes/com/example/thread/syn/TestSynchronized.class
  Last modified 2021-4-24; size 1716 bytes
  MD5 checksum b4bf2ea2539f26ae53bcaa6d25c15908
  Compiled from "TestSynchronized.java"
public class com.example.thread.syn.TestSynchronized
  minor version: 0
  major version: 52
  flags: ACC_PUBLIC, ACC_SUPER
Constant pool:
   #1 = Methodref          #27.#50        // java/lang/Object."<init>":()V
   #2 = Fieldref           #51.#52        // java/lang/System.out:Ljava/io/PrintStream;
   #3 = Class              #53            // java/lang/StringBuilder
   #4 = Methodref          #3.#50         // java/lang/StringBuilder."<init>":()V
   #5 = Methodref          #18.#54        // java/lang/Thread.currentThread:()Ljava/lang/Thread;
   #6 = Methodref          #18.#55        // java/lang/Thread.getName:()Ljava/lang/String;
   #7 = Methodref          #3.#56         // java/lang/StringBuilder.append:(Ljava/lang/String;)Ljava/lang/StringBuilder;
   #8 = String             #57            //  :
   #9 = Methodref          #3.#58         // java/lang/StringBuilder.append:(I)Ljava/lang/StringBuilder;
  #10 = Methodref          #3.#59         // java/lang/StringBuilder.toString:()Ljava/lang/String;
  #11 = Methodref          #60.#61        // java/io/PrintStream.println:(Ljava/lang/String;)V
  #12 = Long               500l
  #14 = Methodref          #18.#62        // java/lang/Thread.sleep:(J)V
  #15 = Class              #63            // java/lang/InterruptedException
  #16 = Class              #64            // com/example/thread/syn/TestSynchronized
  #17 = Methodref          #16.#50        // com/example/thread/syn/TestSynchronized."<init>":()V
  #18 = Class              #65            // java/lang/Thread
  #19 = Class              #66            // com/example/thread/syn/TestSynchronized$1
  #20 = Methodref          #19.#67        // com/example/thread/syn/TestSynchronized$1."<init>":(Lcom/example/thread/syn/TestSynchronized;)V
  #21 = String             #36            // test1
  #22 = Methodref          #18.#68        // java/lang/Thread."<init>":(Ljava/lang/Runnable;Ljava/lang/String;)V
  #23 = Class              #69            // com/example/thread/syn/TestSynchronized$2
  #24 = Methodref          #23.#50        // com/example/thread/syn/TestSynchronized$2."<init>":()V
  #25 = String             #41            // test2
  #26 = Methodref          #18.#70        // java/lang/Thread.start:()V
  #27 = Class              #71            // java/lang/Object
  #28 = Utf8               InnerClasses
  #29 = Utf8               <init>
  #30 = Utf8               ()V
  #31 = Utf8               Code
  #32 = Utf8               LineNumberTable
  #33 = Utf8               LocalVariableTable
  #34 = Utf8               this
  #35 = Utf8               Lcom/example/thread/syn/TestSynchronized;
  #36 = Utf8               test1
  #37 = Utf8               i
  #38 = Utf8               I
  #39 = Utf8               StackMapTable
  #40 = Class              #63            // java/lang/InterruptedException
  #41 = Utf8               test2
  #42 = Utf8               main
  #43 = Utf8               ([Ljava/lang/String;)V
  #44 = Utf8               args
  #45 = Utf8               [Ljava/lang/String;
  #46 = Utf8               myt2
  #47 = Utf8               Ljava/lang/Thread;
  #48 = Utf8               SourceFile
  #49 = Utf8               TestSynchronized.java
  #50 = NameAndType        #29:#30        // "<init>":()V
  #51 = Class              #72            // java/lang/System
  #52 = NameAndType        #73:#74        // out:Ljava/io/PrintStream;
  #53 = Utf8               java/lang/StringBuilder
  #54 = NameAndType        #75:#76        // currentThread:()Ljava/lang/Thread;
  #55 = NameAndType        #77:#78        // getName:()Ljava/lang/String;
  #56 = NameAndType        #79:#80        // append:(Ljava/lang/String;)Ljava/lang/StringBuilder;
  #57 = Utf8                :
  #58 = NameAndType        #79:#81        // append:(I)Ljava/lang/StringBuilder;
  #59 = NameAndType        #82:#78        // toString:()Ljava/lang/String;
  #60 = Class              #83            // java/io/PrintStream
  #61 = NameAndType        #84:#85        // println:(Ljava/lang/String;)V
  #62 = NameAndType        #86:#87        // sleep:(J)V
  #63 = Utf8               java/lang/InterruptedException
  #64 = Utf8               com/example/thread/syn/TestSynchronized
  #65 = Utf8               java/lang/Thread
  #66 = Utf8               com/example/thread/syn/TestSynchronized$1
  #67 = NameAndType        #29:#88        // "<init>":(Lcom/example/thread/syn/TestSynchronized;)V
  #68 = NameAndType        #29:#89        // "<init>":(Ljava/lang/Runnable;Ljava/lang/String;)V
  #69 = Utf8               com/example/thread/syn/TestSynchronized$2
  #70 = NameAndType        #90:#30        // start:()V
  #71 = Utf8               java/lang/Object
  #72 = Utf8               java/lang/System
  #73 = Utf8               out
  #74 = Utf8               Ljava/io/PrintStream;
  #75 = Utf8               currentThread
  #76 = Utf8               ()Ljava/lang/Thread;
  #77 = Utf8               getName
  #78 = Utf8               ()Ljava/lang/String;
  #79 = Utf8               append
  #80 = Utf8               (Ljava/lang/String;)Ljava/lang/StringBuilder;
  #81 = Utf8               (I)Ljava/lang/StringBuilder;
  #82 = Utf8               toString
  #83 = Utf8               java/io/PrintStream
  #84 = Utf8               println
  #85 = Utf8               (Ljava/lang/String;)V
  #86 = Utf8               sleep
  #87 = Utf8               (J)V
  #88 = Utf8               (Lcom/example/thread/syn/TestSynchronized;)V
  #89 = Utf8               (Ljava/lang/Runnable;Ljava/lang/String;)V
  #90 = Utf8               start
{
  public com.example.thread.syn.TestSynchronized();
    descriptor: ()V
    flags: ACC_PUBLIC
    Code:
      stack=1, locals=1, args_size=1
         0: aload_0
         1: invokespecial #1                  // Method java/lang/Object."<init>":()V
         4: return
      LineNumberTable:
        line 6: 0
      LocalVariableTable:
        Start  Length  Slot  Name   Signature
            0       5     0  this   Lcom/example/thread/syn/TestSynchronized;
#######普通方法#######
  public synchronized void test1();
    descriptor: ()V
    flags: ACC_PUBLIC, ACC_SYNCHRONIZED
    Code:
      stack=3, locals=3, args_size=1
         0: iconst_5
         1: istore_1
         2: iload_1
         3: iinc          1, -1
         6: ifle          56
         9: getstatic     #2                  // Field java/lang/System.out:Ljava/io/PrintStream;
        12: new           #3                  // class java/lang/StringBuilder
        15: dup
        16: invokespecial #4                  // Method java/lang/StringBuilder."<init>":()V
        19: invokestatic  #5                  // Method java/lang/Thread.currentThread:()Ljava/lang/Thread;
        22: invokevirtual #6                  // Method java/lang/Thread.getName:()Ljava/lang/String;
        25: invokevirtual #7                  // Method java/lang/StringBuilder.append:(Ljava/lang/String;)Ljava/lang/StringBuilder;
        28: ldc           #8                  // String  :
        30: invokevirtual #7                  // Method java/lang/StringBuilder.append:(Ljava/lang/String;)Ljava/lang/StringBuilder;
        33: iload_1
        34: invokevirtual #9                  // Method java/lang/StringBuilder.append:(I)Ljava/lang/StringBuilder;
        37: invokevirtual #10                 // Method java/lang/StringBuilder.toString:()Ljava/lang/String;
        40: invokevirtual #11                 // Method java/io/PrintStream.println:(Ljava/lang/String;)V
        43: ldc2_w        #12                 // long 500l
        46: invokestatic  #14                 // Method java/lang/Thread.sleep:(J)V
        49: goto          2
        52: astore_2
        53: goto          2
        56: return
      Exception table:
         from    to  target type
            43    49    52   Class java/lang/InterruptedException
      LineNumberTable:
        line 9: 0
        line 10: 2
        line 11: 9
        line 13: 43
        line 15: 49
        line 14: 52
        line 15: 53
        line 17: 56
      LocalVariableTable:
        Start  Length  Slot  Name   Signature
            0      57     0  this   Lcom/example/thread/syn/TestSynchronized;
            2      55     1     i   I
      StackMapTable: number_of_entries = 3
        frame_type = 252 /* append */
          offset_delta = 2
          locals = [ int ]
        frame_type = 113 /* same_locals_1_stack_item */
          stack = [ class java/lang/InterruptedException ]
        frame_type = 3 /* same */
#######普通方法代码块#######
  public static synchronized void test2();
    descriptor: ()V
    flags: ACC_PUBLIC, ACC_STATIC, ACC_SYNCHRONIZED
    Code:
      stack=3, locals=2, args_size=0
         0: iconst_5
         1: istore_0
         2: iload_0
         3: iinc          0, -1
         6: ifle          56
         9: getstatic     #2                  // Field java/lang/System.out:Ljava/io/PrintStream;
        12: new           #3                  // class java/lang/StringBuilder
        15: dup
        16: invokespecial #4                  // Method java/lang/StringBuilder."<init>":()V
        19: invokestatic  #5                  // Method java/lang/Thread.currentThread:()Ljava/lang/Thread;
        22: invokevirtual #6                  // Method java/lang/Thread.getName:()Ljava/lang/String;
        25: invokevirtual #7                  // Method java/lang/StringBuilder.append:(Ljava/lang/String;)Ljava/lang/StringBuilder;
        28: ldc           #8                  // String  :
        30: invokevirtual #7                  // Method java/lang/StringBuilder.append:(Ljava/lang/String;)Ljava/lang/StringBuilder;
        33: iload_0
        34: invokevirtual #9                  // Method java/lang/StringBuilder.append:(I)Ljava/lang/StringBuilder;
        37: invokevirtual #10                 // Method java/lang/StringBuilder.toString:()Ljava/lang/String;
        40: invokevirtual #11                 // Method java/io/PrintStream.println:(Ljava/lang/String;)V
        43: ldc2_w        #12                 // long 500l
        46: invokestatic  #14                 // Method java/lang/Thread.sleep:(J)V
        49: goto          2
        52: astore_1
        53: goto          2
        56: return
      Exception table:
         from    to  target type
            43    49    52   Class java/lang/InterruptedException
      LineNumberTable:
        line 20: 0
        line 21: 2
        line 22: 9
        line 24: 43
        line 26: 49
        line 25: 52
        line 26: 53
        line 28: 56
      LocalVariableTable:
        Start  Length  Slot  Name   Signature
            2      55     0     i   I
      StackMapTable: number_of_entries = 3
        frame_type = 252 /* append */
          offset_delta = 2
          locals = [ int ]
        frame_type = 113 /* same_locals_1_stack_item */
          stack = [ class java/lang/InterruptedException ]
        frame_type = 3 /* same */

  public static void main(java.lang.String[]);
    descriptor: ([Ljava/lang/String;)V
    flags: ACC_PUBLIC, ACC_STATIC
    Code:
      stack=5, locals=4, args_size=1
         0: new           #16                 // class com/example/thread/syn/TestSynchronized
         3: dup
         4: invokespecial #17                 // Method "<init>":()V
         7: astore_1
         8: new           #18                 // class java/lang/Thread
        11: dup
        12: new           #19                 // class com/example/thread/syn/TestSynchronized$1
        15: dup
        16: aload_1
        17: invokespecial #20                 // Method com/example/thread/syn/TestSynchronized$1."<init>":(Lcom/example/thread/syn/TestSynchronized;)V
        20: ldc           #21                 // String test1
        22: invokespecial #22                 // Method java/lang/Thread."<init>":(Ljava/lang/Runnable;Ljava/lang/String;)V
        25: astore_2
        26: new           #18                 // class java/lang/Thread
        29: dup
        30: new           #23                 // class com/example/thread/syn/TestSynchronized$2
        33: dup
        34: invokespecial #24                 // Method com/example/thread/syn/TestSynchronized$2."<init>":()V
        37: ldc           #25                 // String test2
        39: invokespecial #22                 // Method java/lang/Thread."<init>":(Ljava/lang/Runnable;Ljava/lang/String;)V
        42: astore_3
        43: aload_2
        44: invokevirtual #26                 // Method java/lang/Thread.start:()V
        47: aload_3
        48: invokevirtual #26                 // Method java/lang/Thread.start:()V
        51: return
      LineNumberTable:
        line 35: 0
        line 36: 8
        line 41: 26
        line 46: 43
        line 47: 47
        line 51: 51
      LocalVariableTable:
        Start  Length  Slot  Name   Signature
            0      52     0  args   [Ljava/lang/String;
            8      44     1  myt2   Lcom/example/thread/syn/TestSynchronized;
           26      26     2 test1   Ljava/lang/Thread;
           43       9     3 test2   Ljava/lang/Thread;
}
SourceFile: "TestSynchronized.java"
InnerClasses:
     static #23; //class com/example/thread/syn/TestSynchronized$2
     static #19; //class com/example/thread/syn/TestSynchronized$1


```



















